wormhole_ui/__init__.py
wormhole_ui/errors.py
wormhole_ui/main.py
wormhole_ui/protocol/__init__.py
wormhole_ui/protocol/file_transfer_protocol.py
wormhole_ui/protocol/timeout.py
wormhole_ui/protocol/transit/__init__.py
wormhole_ui/protocol/transit/dest_file.py
wormhole_ui/protocol/transit/file_receiver.py
wormhole_ui/protocol/transit/file_sender.py
wormhole_ui/protocol/transit/progress.py
wormhole_ui/protocol/transit/source_file.py
wormhole_ui/protocol/transit/transit_protocol_base.py
wormhole_ui/protocol/transit/transit_protocol_pair.py
wormhole_ui/protocol/transit/transit_protocol_receiver.py
wormhole_ui/protocol/transit/transit_protocol_sender.py
wormhole_ui/protocol/wormhole_protocol.py
wormhole_ui/resources/README.md
wormhole_ui/resources/check.svg
wormhole_ui/resources/icon.svg
wormhole_ui/resources/icon128.png
wormhole_ui/resources/icon16.png
wormhole_ui/resources/icon24.png
wormhole_ui/resources/icon256.png
wormhole_ui/resources/icon32.png
wormhole_ui/resources/icon48.png
wormhole_ui/resources/icon64.png
wormhole_ui/resources/times.svg
wormhole_ui/resources/wormhole.icns
wormhole_ui/resources/wormhole.ico
wormhole_ui/util.py
wormhole_ui/widgets/connect_dialog.py
wormhole_ui/widgets/errors.py
wormhole_ui/widgets/main_window.py
wormhole_ui/widgets/message_table.py
wormhole_ui/widgets/save_file_dialog.py
wormhole_ui/widgets/shutdown_message.py
wormhole_ui/widgets/ui/ConnectDialog.ui
wormhole_ui/widgets/ui/MainWindow.ui
wormhole_ui/widgets/ui/SaveFile.ui
wormhole_ui/widgets/ui/__init__.py
wormhole_ui/widgets/ui_dialog.py
wormhole_ui-0.2.0.dist-info/entry_points.txt
wormhole_ui-0.2.0.dist-info/LICENSE
wormhole_ui-0.2.0.dist-info/WHEEL
wormhole_ui-0.2.0.dist-info/METADATA
wormhole_ui-0.2.0.dist-info/RECORD
