Metadata-Version: 2.1
Name: wormhole-ui
Version: 0.2.0
Summary: UI for Magic Wormhole - get things from one computer to another safely
Home-page: https://github.com/sneakypete81/wormhole-ui
License: GPL-3.0
Author: sneakypete81
Author-email: sneakypete81@gmail.com
Requires-Python: >=3.6,<3.8
Classifier: Development Status :: 4 - Beta
Classifier: Environment :: MacOS X
Classifier: Environment :: Win32 (MS Windows)
Classifier: Environment :: X11 Applications :: Qt
Classifier: License :: OSI Approved :: GNU General Public License v3 (GPLv3)
Classifier: Programming Language :: Python :: 3
Classifier: Programming Language :: Python :: 3.6
Classifier: Programming Language :: Python :: 3.7
Classifier: Topic :: Security :: Cryptography
Classifier: Topic :: System :: Networking
Classifier: Topic :: System :: Systems Administration
Classifier: Topic :: Utilities
Requires-Dist: PySide2 (==5.13.1)
Requires-Dist: humanize (==0.5.1)
Requires-Dist: magic_wormhole (>=0.11.2,<0.13.0)
Requires-Dist: qt5reactor (>=0.6,<0.7)
Project-URL: Repository, https://github.com/sneakypete81/wormhole-ui
